<?xml version="1.0" encoding="UTF-8"?>
<objects serializationModel="Studio.02.02.00">
	<object class="Event" id="{061f73b3-95cc-4eb8-a237-dbc46e8d52cc}">
		<property name="name">
			<value>Wind</value>
		</property>
		<property name="outputFormat">
			<value>1</value>
		</property>
		<relationship name="folder">
			<destination>{876e43c4-3d95-49ce-a622-505951a93b7a}</destination>
		</relationship>
		<relationship name="mixer">
			<destination>{d9194b69-2ba8-468b-8367-f6b7dbbe8b46}</destination>
		</relationship>
		<relationship name="masterTrack">
			<destination>{719b1f01-9782-4568-be93-6074dc8dfea5}</destination>
		</relationship>
		<relationship name="mixerInput">
			<destination>{37fa5b0b-0dfd-477e-aa19-81382a93ae55}</destination>
		</relationship>
		<relationship name="automatableProperties">
			<destination>{ac9f4155-f612-4863-acf3-fc73049303b0}</destination>
		</relationship>
		<relationship name="markerTracks">
			<destination>{ea974979-fe97-44c6-98b7-951dee8601d8}</destination>
		</relationship>
		<relationship name="groupTracks">
			<destination>{097b48d3-43c1-4ad4-b457-ea5beb502a92}</destination>
		</relationship>
		<relationship name="timeline">
			<destination>{e8cc6848-186c-4169-873d-b10f6536754f}</destination>
		</relationship>
		<relationship name="banks">
			<destination>{4f058086-3189-4edc-b305-b16f10a6189c}</destination>
		</relationship>
	</object>
	<object class="EventMixer" id="{d9194b69-2ba8-468b-8367-f6b7dbbe8b46}">
		<relationship name="masterBus">
			<destination>{084b6d5e-d7f7-420b-a85b-942f9c30ef93}</destination>
		</relationship>
	</object>
	<object class="MasterTrack" id="{719b1f01-9782-4568-be93-6074dc8dfea5}">
		<relationship name="modules">
			<destination>{bea3ee10-6952-4871-9148-b4b1235d6337}</destination>
			<destination>{a3cb9dc7-80dc-4d63-80a0-a475109c5304}</destination>
		</relationship>
		<relationship name="mixerGroup">
			<destination>{084b6d5e-d7f7-420b-a85b-942f9c30ef93}</destination>
		</relationship>
	</object>
	<object class="MixerInput" id="{37fa5b0b-0dfd-477e-aa19-81382a93ae55}">
		<relationship name="effectChain">
			<destination>{679dee7f-0f31-49c1-be77-a9a6360c0ff8}</destination>
		</relationship>
		<relationship name="panner">
			<destination>{e22d1fc2-10da-45bc-94c1-0903dfa0d1e8}</destination>
		</relationship>
		<relationship name="output">
			<destination>{0d91b15b-9dc1-4023-b680-9419661d3dc9}</destination>
		</relationship>
	</object>
	<object class="EventAutomatableProperties" id="{ac9f4155-f612-4863-acf3-fc73049303b0}" />
	<object class="MarkerTrack" id="{ea974979-fe97-44c6-98b7-951dee8601d8}" />
	<object class="GroupTrack" id="{097b48d3-43c1-4ad4-b457-ea5beb502a92}">
		<relationship name="modules">
			<destination>{fe6f5eb7-59c8-4143-a632-c7f5c4937724}</destination>
			<destination>{ee0636ef-a218-409e-8a0e-fdd8cecccd2c}</destination>
			<destination>{eb2c9dfc-c829-46ee-b706-cdfcdfc08bf1}</destination>
		</relationship>
		<relationship name="mixerGroup">
			<destination>{fc573a38-9a92-4643-a6de-9d1c7a469634}</destination>
		</relationship>
	</object>
	<object class="Timeline" id="{e8cc6848-186c-4169-873d-b10f6536754f}">
		<relationship name="modules">
			<destination>{fe6f5eb7-59c8-4143-a632-c7f5c4937724}</destination>
		</relationship>
		<relationship name="markers">
			<destination>{4d89c667-8f36-454c-8218-4d3fcfbdb80c}</destination>
		</relationship>
	</object>
	<object class="EventMixerMaster" id="{084b6d5e-d7f7-420b-a85b-942f9c30ef93}">
		<relationship name="effectChain">
			<destination>{d4a7c0c7-e0d8-4449-b400-c7a0ccc3b631}</destination>
		</relationship>
		<relationship name="panner">
			<destination>{bbe0e67d-d51a-41db-a72e-eec7ebf547f4}</destination>
		</relationship>
		<relationship name="mixer">
			<destination>{d9194b69-2ba8-468b-8367-f6b7dbbe8b46}</destination>
		</relationship>
	</object>
	<object class="TransitionSourceSound" id="{bea3ee10-6952-4871-9148-b4b1235d6337}">
		<property name="length">
			<value>0</value>
		</property>
	</object>
	<object class="TransitionDestinationSound" id="{a3cb9dc7-80dc-4d63-80a0-a475109c5304}">
		<property name="start">
			<value>0.5</value>
		</property>
		<property name="length">
			<value>0</value>
		</property>
	</object>
	<object class="MixerBusEffectChain" id="{679dee7f-0f31-49c1-be77-a9a6360c0ff8}">
		<relationship name="effects">
			<destination>{a0ef69d8-d524-4112-8398-a551934362e5}</destination>
		</relationship>
	</object>
	<object class="MixerBusPanner" id="{e22d1fc2-10da-45bc-94c1-0903dfa0d1e8}" />
	<object class="SingleSound" id="{fe6f5eb7-59c8-4143-a632-c7f5c4937724}">
		<property name="length">
			<value>108</value>
		</property>
		<relationship name="audioFile">
			<destination>{258e36dc-9db8-44bb-8b04-ca4b430c2138}</destination>
		</relationship>
	</object>
	<object class="TransitionSourceSound" id="{ee0636ef-a218-409e-8a0e-fdd8cecccd2c}">
		<property name="length">
			<value>0.5</value>
		</property>
		<relationship name="fadeOutCurve">
			<destination>{53caceb8-0e38-4f1a-b584-0aec87424cb9}</destination>
		</relationship>
	</object>
	<object class="TransitionDestinationSound" id="{eb2c9dfc-c829-46ee-b706-cdfcdfc08bf1}">
		<property name="start">
			<value>3.4694469519536142e-18</value>
		</property>
		<property name="length">
			<value>0.5</value>
		</property>
		<relationship name="fadeInCurve">
			<destination>{7646739b-bef0-4f47-a856-2f79246fa97a}</destination>
		</relationship>
	</object>
	<object class="EventMixerGroup" id="{fc573a38-9a92-4643-a6de-9d1c7a469634}">
		<property name="volume">
			<value>-11.5</value>
		</property>
		<property name="name">
			<value>Audio 1</value>
		</property>
		<relationship name="effectChain">
			<destination>{cc3db606-2435-4b40-8b02-ccff2595a9d5}</destination>
		</relationship>
		<relationship name="panner">
			<destination>{38332c9f-4f23-49b5-8d65-2131884a8807}</destination>
		</relationship>
		<relationship name="output">
			<destination>{084b6d5e-d7f7-420b-a85b-942f9c30ef93}</destination>
		</relationship>
	</object>
	<object class="LoopRegion" id="{4d89c667-8f36-454c-8218-4d3fcfbdb80c}">
		<property name="position">
			<value>0</value>
		</property>
		<property name="length">
			<value>102</value>
		</property>
		<relationship name="timeline">
			<destination>{e8cc6848-186c-4169-873d-b10f6536754f}</destination>
		</relationship>
		<relationship name="markerTrack">
			<destination>{ea974979-fe97-44c6-98b7-951dee8601d8}</destination>
		</relationship>
		<relationship name="transitionTimeline">
			<destination>{6baf0526-f6d4-4d2b-a856-abb94f1966bb}</destination>
		</relationship>
	</object>
	<object class="MixerBusEffectChain" id="{d4a7c0c7-e0d8-4449-b400-c7a0ccc3b631}">
		<relationship name="effects">
			<destination>{4ca6688c-9f73-4dc6-858c-bc6aa1f5e178}</destination>
		</relationship>
	</object>
	<object class="MixerBusPanner" id="{bbe0e67d-d51a-41db-a72e-eec7ebf547f4}" />
	<object class="MixerBusFader" id="{a0ef69d8-d524-4112-8398-a551934362e5}" />
	<object class="TransitionSourceFadeOutCurve" id="{53caceb8-0e38-4f1a-b584-0aec87424cb9}">
		<relationship name="startPoint">
			<destination>{507c9136-8e2f-4904-a3b4-ea0e48a76e98}</destination>
		</relationship>
		<relationship name="endPoint">
			<destination>{92a90772-15fa-4626-af96-1a1eece45fb9}</destination>
		</relationship>
		<relationship name="relatedModule">
			<destination>{eb2c9dfc-c829-46ee-b706-cdfcdfc08bf1}</destination>
		</relationship>
	</object>
	<object class="TransitionDestinationFadeInCurve" id="{7646739b-bef0-4f47-a856-2f79246fa97a}">
		<relationship name="startPoint">
			<destination>{69489460-fe86-4e90-9a64-81d952d54c3b}</destination>
		</relationship>
		<relationship name="endPoint">
			<destination>{b1360148-d0c1-4b23-a4c3-46b2e89a2507}</destination>
		</relationship>
		<relationship name="relatedModule">
			<destination>{ee0636ef-a218-409e-8a0e-fdd8cecccd2c}</destination>
		</relationship>
	</object>
	<object class="MixerBusEffectChain" id="{cc3db606-2435-4b40-8b02-ccff2595a9d5}">
		<relationship name="effects">
			<destination>{c74f7711-83d8-4c93-a90b-a33f09a9cc83}</destination>
		</relationship>
	</object>
	<object class="MixerBusPanner" id="{38332c9f-4f23-49b5-8d65-2131884a8807}" />
	<object class="TransitionTimeline" id="{6baf0526-f6d4-4d2b-a856-abb94f1966bb}">
		<property name="length">
			<value>0.5</value>
		</property>
		<relationship name="modules">
			<destination>{ee0636ef-a218-409e-8a0e-fdd8cecccd2c}</destination>
			<destination>{eb2c9dfc-c829-46ee-b706-cdfcdfc08bf1}</destination>
			<destination>{bea3ee10-6952-4871-9148-b4b1235d6337}</destination>
			<destination>{a3cb9dc7-80dc-4d63-80a0-a475109c5304}</destination>
		</relationship>
	</object>
	<object class="MixerBusFader" id="{4ca6688c-9f73-4dc6-858c-bc6aa1f5e178}" />
	<object class="AutomationPoint" id="{507c9136-8e2f-4904-a3b4-ea0e48a76e98}">
		<property name="position">
			<value>3.4694469519536142e-18</value>
		</property>
		<property name="value">
			<value>1</value>
		</property>
		<property name="curveShape">
			<value>0.25471893</value>
		</property>
	</object>
	<object class="AutomationPoint" id="{92a90772-15fa-4626-af96-1a1eece45fb9}">
		<property name="position">
			<value>0.5</value>
		</property>
		<property name="value">
			<value>0</value>
		</property>
	</object>
	<object class="AutomationPoint" id="{69489460-fe86-4e90-9a64-81d952d54c3b}">
		<property name="position">
			<value>3.4694469519536142e-18</value>
		</property>
		<property name="value">
			<value>0</value>
		</property>
		<property name="curveShape">
			<value>-0.2547189</value>
		</property>
	</object>
	<object class="AutomationPoint" id="{b1360148-d0c1-4b23-a4c3-46b2e89a2507}">
		<property name="position">
			<value>0.5</value>
		</property>
		<property name="value">
			<value>1</value>
		</property>
	</object>
	<object class="MixerBusFader" id="{c74f7711-83d8-4c93-a90b-a33f09a9cc83}" />
</objects>
