<?xml version="1.0" encoding="UTF-8"?>
<objects serializationModel="Studio.02.02.00">
	<object class="Snapshot" id="{9009021a-e853-41ff-a978-ee983108ee56}">
		<property name="name">
			<value>InsideHouse</value>
		</property>
		<property name="behavior">
			<value>1</value>
		</property>
		<relationship name="mixer">
			<destination>{dea676ef-c66d-4960-bcbc-4a4331feb245}</destination>
		</relationship>
		<relationship name="automatableProperties">
			<destination>{fb56e85d-aa6f-4154-a987-435940873b7c}</destination>
		</relationship>
		<relationship name="markerTracks">
			<destination>{aaaa0380-30ef-4be4-b8b7-c20e29c9c4aa}</destination>
		</relationship>
		<relationship name="timeline">
			<destination>{2d68efe8-4c20-4c6d-9243-b06e7c074c08}</destination>
		</relationship>
		<relationship name="snapshotMasterTrack">
			<destination>{1b753082-c8c4-4812-91db-89ad9ce9d582}</destination>
		</relationship>
		<relationship name="snapshotProperties">
			<destination>{2531608e-de6c-43b8-b4c0-9c72e813ddb9}</destination>
			<destination>{1b954b88-4966-4d60-a738-1b2da6945ac2}</destination>
		</relationship>
		<relationship name="snapshotTracks">
			<destination>{f77c2fcb-f4a0-4353-896d-b3a60548ba97}</destination>
			<destination>{e5c3054a-989b-4e0e-b9fc-e1dbee50be4e}</destination>
			<destination>{2904d3fa-eaa4-4a74-b3b7-04a692a07432}</destination>
		</relationship>
	</object>
	<object class="EventAutomatableProperties" id="{fb56e85d-aa6f-4154-a987-435940873b7c}">
		<relationship name="modulators">
			<destination>{b1c015a0-625e-40bf-9948-1f668a826b21}</destination>
		</relationship>
	</object>
	<object class="MarkerTrack" id="{aaaa0380-30ef-4be4-b8b7-c20e29c9c4aa}" />
	<object class="Timeline" id="{2d68efe8-4c20-4c6d-9243-b06e7c074c08}" />
	<object class="SnapshotMasterTrack" id="{1b753082-c8c4-4812-91db-89ad9ce9d582}" />
	<object class="SnapshotProperty" id="{2531608e-de6c-43b8-b4c0-9c72e813ddb9}">
		<property name="propertyName">
			<value>frequencyA</value>
		</property>
		<property name="value">
			<value>300</value>
		</property>
		<relationship name="automatableObject">
			<destination>{03a8d9d0-43b3-4b1e-aba0-f6dd8db4b445}</destination>
		</relationship>
	</object>
	<object class="SnapshotProperty" id="{1b954b88-4966-4d60-a738-1b2da6945ac2}">
		<property name="propertyName">
			<value>volume</value>
		</property>
		<property name="value">
			<value>3</value>
		</property>
		<relationship name="automatableObject">
			<destination>{7c795e2b-5076-4a6b-a637-134e2b049e8f}</destination>
		</relationship>
	</object>
	<object class="SnapshotTrack" id="{f77c2fcb-f4a0-4353-896d-b3a60548ba97}">
		<relationship name="mixerStrip">
			<destination>{67a36213-d923-4d7f-a65b-235d8488de19}</destination>
		</relationship>
	</object>
	<object class="SnapshotTrack" id="{e5c3054a-989b-4e0e-b9fc-e1dbee50be4e}">
		<relationship name="mixerStrip">
			<destination>{363d862b-28ad-4c8a-b25e-6dbcbfe51a60}</destination>
		</relationship>
	</object>
	<object class="SnapshotTrack" id="{2904d3fa-eaa4-4a74-b3b7-04a692a07432}">
		<relationship name="mixerStrip">
			<destination>{7c795e2b-5076-4a6b-a637-134e2b049e8f}</destination>
		</relationship>
	</object>
	<object class="ADSRModulator" id="{b1c015a0-625e-40bf-9948-1f668a826b21}">
		<property name="nameOfPropertyBeingModulated">
			<value>snapshotIntensity</value>
		</property>
		<property name="peakValue">
			<value>100</value>
		</property>
		<property name="sustainValue">
			<value>100</value>
		</property>
	</object>
</objects>
